wsync/__init__.py
wsync/__main__.py
wsync/wsync.py
wsync/tests/__init__.py
wsync/tests/test.py
wsync-0.9.2.dist-info/METADATA
wsync-0.9.2.dist-info/RECORD
wsync-0.9.2.dist-info/WHEEL
wsync-0.9.2.dist-info/entry_points.txt
wsync-0.9.2.dist-info/top_level.txt
