Metadata-Version: 2.1
Name: wsync
Version: 0.9.2
Summary: A small utility for synchronizing a local folder with a remote web repository
Home-page: https://github.com/robertoreale/wsync
Author: Roberto Reale
Author-email: rober.reale@gmail.com
License: UNKNOWN
Keywords: wsync,sync,http,https,web
Platform: UNKNOWN
Requires-Dist: requests
Requires-Dist: PyYAML
Requires-Dist: pyCheckableString
